fractalpaths/__init__.py
fractalpaths/fractal.py
fractalpaths-0.0.1.dist-info/LICENSE
fractalpaths-0.0.1.dist-info/METADATA
fractalpaths-0.0.1.dist-info/WHEEL
fractalpaths-0.0.1.dist-info/top_level.txt
fractalpaths-0.0.1.dist-info/RECORD
