Metadata-Version: 2.1
Name: fractalpaths
Version: 0.0.1
Summary: Given a fractal and two points in the fractal, finds the shortest taxicab path between the points that stays in the fractal
Home-page: https://github.com/karangoe/fractalpaths
Author: Elene Karangozishvili
Author-email: elenekarangozishvili@gmail.com
License: UNKNOWN
Platform: UNKNOWN
Classifier: Programming Language :: Python :: 3
Classifier: License :: OSI Approved :: MIT License
Classifier: Operating System :: OS Independent
Requires-Python: >=3.8
